_mcpl_extra/__init__.py
_mcpl_extra/cli.py
_mcpl_extra/data/bin/mcpl2phits
_mcpl_extra/data/bin/mcpl2ssw
_mcpl_extra/data/bin/phits2mcpl
_mcpl_extra/data/bin/ssw2mcpl
mcpl_extra-2.2.6.dist-info/METADATA
mcpl_extra-2.2.6.dist-info/WHEEL
mcpl_extra-2.2.6.dist-info/entry_points.txt
mcpl_extra-2.2.6.dist-info/RECORD
mcpl_extra-2.2.6.dist-info/licenses/LICENSE
