Metadata-Version: 2.2
Name: mcpl-extra
Version: 2.2.6
Summary: Various tools and conversion utilities related to MCPL files.
Author: MCPL developers (Thomas Kittelmann, et. al.)
License: Apache-2.0
Classifier: Programming Language :: Python :: 3
Classifier: License :: OSI Approved :: Apache Software License
Project-URL: Homepage, https://mctools.github.io/mcpl/
Project-URL: Bug Tracker, https://github.com/mctools/mcpl/issues
Requires-Python: >=3.8
Requires-Dist: mcpl-core==2.2.6
